quart_tasks-0.5.0.dist-info/METADATA
quart_tasks-0.5.0.dist-info/WHEEL
quart_tasks-0.5.0.dist-info/entry_points.txt
quart_tasks-0.5.0.dist-info/licenses/LICENSE
quart_tasks/__init__.py
quart_tasks/extension.py
quart_tasks/py.typed
quart_tasks/signals.py
quart_tasks/store.py
quart_tasks-0.5.0.dist-info/RECORD
